{"nodes":[{"nodeID":"552497","text":"Fiona Bruce : This is the WHO, the World Health Organisation","type":"L","timestamp":"2020-06-18 19:55:25"},{"nodeID":"552499","text":"Pure Questioning","type":"YA","timestamp":"2020-06-18 19:55:25","scheme":"PureQuestioning","schemeID":"91"},{"nodeID":"552501","text":"xxx is the WHO, the World Health Organisation","type":"I","timestamp":"2020-06-18 19:55:25"},{"nodeID":"552503","text":"Anon: Fiona Bruce : This is the WHO, the World Health Organisation","type":"L","timestamp":"2020-06-18 19:55:25"},{"nodeID":"552505","text":"Rocco Forte :  Yes","type":"L","timestamp":"2020-06-18 19:55:26"},{"nodeID":"552507","text":"Anon: Rocco Forte :  Yes","type":"L","timestamp":"2020-06-18 19:55:26"},{"nodeID":"552509","text":"Agreeing","type":"YA","timestamp":"2020-06-18 19:55:26","scheme":"Agreeing","schemeID":"77"},{"nodeID":"552511","text":"Default Transition","type":"TA","timestamp":"2020-06-18 19:55:26","scheme":"Default Transition","schemeID":"82"},{"nodeID":"552512","text":"Rocco Forte : The reality in continental Europe, is that they\u2019ve gone back to one metre","type":"L","timestamp":"2020-06-18 19:55:26"},{"nodeID":"552514","text":"Asserting","type":"YA","timestamp":"2020-06-18 19:55:26","scheme":"Asserting","schemeID":"74"},{"nodeID":"552516","text":"the reality in continental Europe, is that Europe has gone back to one metre","type":"I","timestamp":"2020-06-18 19:55:27"},{"nodeID":"552518","text":"Anon: Rocco Forte : The reality in continental Europe, which has started to open up, is that they\u2019ve gone back to one metre","type":"L","timestamp":"2020-06-18 19:55:27"},{"nodeID":"552520","text":"Default Transition","type":"TA","timestamp":"2020-06-18 19:55:27","scheme":"Default Transition","schemeID":"82"},{"nodeID":"552522","text":"Rocco Forte : which has started to open up","type":"L","timestamp":"2020-06-18 19:55:27"},{"nodeID":"552524","text":"Asserting","type":"YA","timestamp":"2020-06-18 19:55:27","scheme":"Asserting","schemeID":"74"},{"nodeID":"552526","text":"Europe has started to open up","type":"I","timestamp":"2020-06-18 19:55:27"},{"nodeID":"552528","text":"Anon: Rocco Forte : which has started to open up","type":"L","timestamp":"2020-06-18 19:55:27"},{"nodeID":"552530","text":"Default Transition","type":"TA","timestamp":"2020-06-18 19:55:28","scheme":"Default Transition","schemeID":"82"},{"nodeID":"552532","text":"Anon: Rocco Forte :  Some of them","type":"L","timestamp":"2020-06-18 19:55:28"},{"nodeID":"552534","text":"Fiona Bruce : Some of them","type":"L","timestamp":"2020-06-18 19:55:28"},{"nodeID":"552536","text":"Asserting","type":"YA","timestamp":"2020-06-18 19:55:28","scheme":"Asserting","schemeID":"74"},{"nodeID":"552538","text":"some of the European countries have opened up","type":"I","timestamp":"2020-06-18 19:55:28"},{"nodeID":"552539","text":"Anon: Fiona Bruce : Some of them","type":"L","timestamp":"2020-06-18 19:55:28"},{"nodeID":"552541","text":"Default Transition","type":"TA","timestamp":"2020-06-18 19:55:29","scheme":"Default Transition","schemeID":"82"},{"nodeID":"552543","text":"Fiona Bruce :  not all of them have","type":"L","timestamp":"2020-06-18 19:55:29"},{"nodeID":"552545","text":"Asserting","type":"YA","timestamp":"2020-06-18 19:55:29","scheme":"Asserting","schemeID":"74"},{"nodeID":"552546","text":"not all of the European countries opened up","type":"I","timestamp":"2020-06-18 19:55:29"},{"nodeID":"552547","text":"Anon: Fiona Bruce :  not all of them have","type":"L","timestamp":"2020-06-18 19:55:29"},{"nodeID":"552548","text":"Default Transition","type":"TA","timestamp":"2020-06-18 19:55:29","scheme":"Default Transition","schemeID":"82"},{"nodeID":"552549","text":"Default Rephrase","type":"MA","timestamp":"2020-06-18 19:55:29","scheme":"Default Rephrase","schemeID":"144"},{"nodeID":"552550","text":"Restating","type":"YA","timestamp":"2020-06-18 19:55:30","scheme":"Restating","schemeID":"101"},{"nodeID":"552551","text":"Default Inference","type":"RA","timestamp":"2020-06-18 19:55:30","scheme":"Default Inference","schemeID":"72"},{"nodeID":"552552","text":"Arguing","type":"YA","timestamp":"2020-06-18 19:55:30","scheme":"Arguing","schemeID":"80"},{"nodeID":"552553","text":"Default Conflict","type":"CA","timestamp":"2020-06-18 19:55:30","scheme":"Default Conflict","schemeID":"71"},{"nodeID":"552554","text":"Disagreeing","type":"YA","timestamp":"2020-06-18 19:55:30","scheme":"Disagreeing","schemeID":"78"},{"nodeID":"552555","text":"Anon: Fiona Bruce :  some of them have","type":"L","timestamp":"2020-06-18 19:55:30"},{"nodeID":"552556","text":"Fiona Bruce : yes, some of them have","type":"L","timestamp":"2020-06-18 19:55:30"},{"nodeID":"552557","text":"Asserting","type":"YA","timestamp":"2020-06-18 19:55:31","scheme":"Asserting","schemeID":"74"},{"nodeID":"552558","text":"yes, some of the European countries have opened up","type":"I","timestamp":"2020-06-18 19:55:31"},{"nodeID":"552559","text":"Anon: Fiona Bruce : yes, some of them have","type":"L","timestamp":"2020-06-18 19:55:31"},{"nodeID":"552560","text":"Default Transition","type":"TA","timestamp":"2020-06-18 19:55:31","scheme":"Default Transition","schemeID":"82"},{"nodeID":"552561","text":"Default Rephrase","type":"MA","timestamp":"2020-06-18 19:55:31","scheme":"Default Rephrase","schemeID":"144"},{"nodeID":"552562","text":"Restating","type":"YA","timestamp":"2020-06-18 19:55:31","scheme":"Restating","schemeID":"101"},{"nodeID":"552563","text":"Fiona Bruce : what have we got","type":"L","timestamp":"2020-06-18 19:55:31"},{"nodeID":"552564","text":"Pure Questioning","type":"YA","timestamp":"2020-06-18 19:55:32","scheme":"PureQuestioning","schemeID":"91"},{"nodeID":"552565","text":"xxx is what we have got","type":"I","timestamp":"2020-06-18 19:55:32"},{"nodeID":"552566","text":"Anon: Fiona Bruce : what have we got","type":"L","timestamp":"2020-06-18 19:55:32"},{"nodeID":"552567","text":"Default Transition","type":"TA","timestamp":"2020-06-18 19:55:32","scheme":"Default Transition","schemeID":"82"},{"nodeID":"552568","text":"Fiona Bruce : We\u2019ve got China","type":"L","timestamp":"2020-06-18 19:55:32"},{"nodeID":"552569","text":"Assertive Questioning","type":"YA","timestamp":"2020-06-18 19:55:32","scheme":"AssertiveQuestioning","schemeID":"73"},{"nodeID":"552570","text":"China is what we have got","type":"I","timestamp":"2020-06-18 19:55:32"},{"nodeID":"552571","text":"Anon: Fiona Bruce : We\u2019ve got China","type":"L","timestamp":"2020-06-18 19:55:33"},{"nodeID":"552572","text":"Default Transition","type":"TA","timestamp":"2020-06-18 19:55:33","scheme":"Default Transition","schemeID":"82"},{"nodeID":"552573","text":"Rocco Forte :  A lot of them have","type":"L","timestamp":"2020-06-18 19:55:33"},{"nodeID":"552574","text":"Asserting","type":"YA","timestamp":"2020-06-18 19:55:33","scheme":"Asserting","schemeID":"74"},{"nodeID":"552575","text":"a lot of the European countries have opened up","type":"I","timestamp":"2020-06-18 19:55:33"},{"nodeID":"552576","text":"Anon: Rocco Forte :  A lot of them have","type":"L","timestamp":"2020-06-18 19:55:33"},{"nodeID":"552577","text":"Default Rephrase","type":"MA","timestamp":"2020-06-18 19:55:33","scheme":"Default Rephrase","schemeID":"144"},{"nodeID":"552578","text":"Default Illocuting","type":"YA","timestamp":"2020-06-18 19:55:34","scheme":"Default Illocuting","schemeID":"168"},{"nodeID":"552579","text":"Default Rephrase","type":"MA","timestamp":"2020-06-18 19:55:34","scheme":"Default Rephrase","schemeID":"144"},{"nodeID":"552580","text":"Default Transition","type":"TA","timestamp":"2020-06-18 19:55:34","scheme":"Default Transition","schemeID":"82"},{"nodeID":"552581","text":"Restating","type":"YA","timestamp":"2020-06-18 19:55:34","scheme":"Restating","schemeID":"101"},{"nodeID":"552582","text":"Rocco Forte : Italy has and Germany has","type":"L","timestamp":"2020-06-18 19:55:34"},{"nodeID":"552583","text":"Asserting","type":"YA","timestamp":"2020-06-18 19:55:34","scheme":"Asserting","schemeID":"74"},{"nodeID":"552584","text":"Italy has opened up and Germany has opened up","type":"I","timestamp":"2020-06-18 19:55:34"},{"nodeID":"552585","text":"Anon: Rocco Forte : Italy has and Germany has","type":"L","timestamp":"2020-06-18 19:55:35"},{"nodeID":"552586","text":"Default Transition","type":"TA","timestamp":"2020-06-18 19:55:35","scheme":"Default Transition","schemeID":"82"},{"nodeID":"552587","text":"Default Rephrase","type":"MA","timestamp":"2020-06-18 19:55:35","scheme":"Default Rephrase","schemeID":"144"},{"nodeID":"552588","text":"Restating","type":"YA","timestamp":"2020-06-18 19:55:35","scheme":"Restating","schemeID":"101"},{"nodeID":"552589","text":"Fiona Bruce : Germany is at one and a half metres, as is Italy","type":"L","timestamp":"2020-06-18 19:55:35"},{"nodeID":"552590","text":"Asserting","type":"YA","timestamp":"2020-06-18 19:55:35","scheme":"Asserting","schemeID":"74"},{"nodeID":"552591","text":"Germany is at one and a half metres, as is Italy","type":"I","timestamp":"2020-06-18 19:55:35"},{"nodeID":"552592","text":"Anon: Fiona Bruce : Germany is at one and a half metres, as is Italy","type":"L","timestamp":"2020-06-18 19:55:36"},{"nodeID":"552593","text":"Default Transition","type":"TA","timestamp":"2020-06-18 19:55:36","scheme":"Default Transition","schemeID":"82"},{"nodeID":"552594","text":"Default Conflict","type":"CA","timestamp":"2020-06-18 19:55:36","scheme":"Default Conflict","schemeID":"71"},{"nodeID":"552595","text":"Disagreeing","type":"YA","timestamp":"2020-06-18 19:55:36","scheme":"Disagreeing","schemeID":"78"},{"nodeID":"552596","text":"Fiona Bruce : France and Denmark are at one metre at the moment","type":"L","timestamp":"2020-06-18 19:55:36"},{"nodeID":"552597","text":"Asserting","type":"YA","timestamp":"2020-06-18 19:55:36","scheme":"Asserting","schemeID":"74"},{"nodeID":"552598","text":"France and Denmark are at one metre at the moment","type":"I","timestamp":"2020-06-18 19:55:36"},{"nodeID":"552599","text":"Anon: Fiona Bruce : France and Denmark are at one metre at the moment","type":"L","timestamp":"2020-06-18 19:55:37"},{"nodeID":"552600","text":"Default Transition","type":"TA","timestamp":"2020-06-18 19:55:37","scheme":"Default Transition","schemeID":"82"},{"nodeID":"552601","text":"Liz SavilleRoberts : Spain is higher","type":"L","timestamp":"2020-06-18 19:55:37"},{"nodeID":"552602","text":"Asserting","type":"YA","timestamp":"2020-06-18 19:55:37","scheme":"Asserting","schemeID":"74"},{"nodeID":"552603","text":"Spain has higher restictions than France and Denmark","type":"I","timestamp":"2020-06-18 19:55:37"},{"nodeID":"552604","text":"Anon: Liz SavilleRoberts : Spain is higher","type":"L","timestamp":"2020-06-18 19:55:37"},{"nodeID":"552605","text":"Default Transition","type":"TA","timestamp":"2020-06-18 19:55:38","scheme":"Default Transition","schemeID":"82"},{"nodeID":"552606","text":"Rocco Forte :  the reality of this whole thing, is no one is concentrating on the economic impacts of this","type":"L","timestamp":"2020-06-18 19:55:38"},{"nodeID":"552607","text":"Asserting","type":"YA","timestamp":"2020-06-18 19:55:38","scheme":"Asserting","schemeID":"74"},{"nodeID":"552608","text":"the reality of this whole thing, is no one is concentrating on the economic impacts of the pandemic","type":"I","timestamp":"2020-06-18 19:55:38"},{"nodeID":"552609","text":"Anon: Rocco Forte :  the reality of this whole thing, is no one is concentrating on the economic impacts of this","type":"L","timestamp":"2020-06-18 19:55:38"},{"nodeID":"552610","text":"Default Transition","type":"TA","timestamp":"2020-06-18 19:55:38","scheme":"Default Transition","schemeID":"82"},{"nodeID":"552611","text":"Rocco Forte :  the reality of this disease is it\u2019s not turned out to be like that","type":"L","timestamp":"2020-06-18 19:55:38"},{"nodeID":"552612","text":"Asserting","type":"YA","timestamp":"2020-06-18 19:55:39","scheme":"Asserting","schemeID":"74"},{"nodeID":"552613","text":"the reality of this disease is that it\u2019s not turned out to be a terrible diesease","type":"I","timestamp":"2020-06-18 19:55:39"},{"nodeID":"552614","text":"Anon: Rocco Forte :  the reality of this disease, which at first was thought to be a terrible disease, and was going to kill millions of people, it\u2019s not turned out to be like that","type":"L","timestamp":"2020-06-18 19:55:39"},{"nodeID":"552615","text":"Default Transition","type":"TA","timestamp":"2020-06-18 19:55:39","scheme":"Default Transition","schemeID":"82"},{"nodeID":"552616","text":"Rocco Forte :  which at first was thought to be a terrible disease","type":"L","timestamp":"2020-06-18 19:55:39"},{"nodeID":"552617","text":"Asserting","type":"YA","timestamp":"2020-06-18 19:55:39","scheme":"Asserting","schemeID":"74"},{"nodeID":"552618","text":"the pandemic at first was thought to be a terrible disease","type":"I","timestamp":"2020-06-18 19:55:39"},{"nodeID":"552619","text":"Anon: Rocco Forte :  which at first was thought to be a terrible disease","type":"L","timestamp":"2020-06-18 19:55:40"},{"nodeID":"552620","text":"Default Transition","type":"TA","timestamp":"2020-06-18 19:55:40","scheme":"Default Transition","schemeID":"82"},{"nodeID":"552621","text":"Rocco Forte : was going to kill millions of people","type":"L","timestamp":"2020-06-18 19:55:40"},{"nodeID":"552622","text":"Asserting","type":"YA","timestamp":"2020-06-18 19:55:40","scheme":"Asserting","schemeID":"74"},{"nodeID":"552623","text":"the pandemic was thought to kill millions of people","type":"I","timestamp":"2020-06-18 19:55:40"},{"nodeID":"552624","text":"Anon: Rocco Forte : was going to kill millions of people","type":"L","timestamp":"2020-06-18 19:55:40"},{"nodeID":"552625","text":"Default Inference","type":"RA","timestamp":"2020-06-18 19:55:41","scheme":"Default Inference","schemeID":"72"},{"nodeID":"552626","text":"Default Transition","type":"TA","timestamp":"2020-06-18 19:55:41","scheme":"Default Transition","schemeID":"82"},{"nodeID":"552627","text":"Arguing","type":"YA","timestamp":"2020-06-18 19:55:41","scheme":"Arguing","schemeID":"80"},{"nodeID":"552628","text":"Rocco Forte : A lot of the surveys that have been done show it\u2019s 0.1 to 0.2 per cent of people, who die","type":"L","timestamp":"2020-06-18 19:55:41"},{"nodeID":"552629","text":"Asserting","type":"YA","timestamp":"2020-06-18 19:55:41","scheme":"Asserting","schemeID":"74"},{"nodeID":"552630","text":"a lot of the surveys that have been done show it\u2019s 0.1 to 0.2 per cent of people, who die","type":"I","timestamp":"2020-06-18 19:55:41"},{"nodeID":"552631","text":"Anon: Rocco Forte : A lot of the surveys that have been done show it\u2019s 0.1 to 0.2 per cent of people, who die","type":"L","timestamp":"2020-06-18 19:55:41"},{"nodeID":"552632","text":"Default Inference","type":"RA","timestamp":"2020-06-18 19:55:42","scheme":"Default Inference","schemeID":"72"},{"nodeID":"552633","text":"Default Transition","type":"TA","timestamp":"2020-06-18 19:55:42","scheme":"Default Transition","schemeID":"82"},{"nodeID":"552634","text":"Arguing","type":"YA","timestamp":"2020-06-18 19:55:42","scheme":"Arguing","schemeID":"80"},{"nodeID":"552635","text":"Rocco Forte :  if they catch the disease","type":"L","timestamp":"2020-06-18 19:55:42"},{"nodeID":"552636","text":"Asserting","type":"YA","timestamp":"2020-06-18 19:55:42","scheme":"Asserting","schemeID":"74"},{"nodeID":"552637","text":"if they catch the disease 0.1 to 0.2 percent of people die","type":"I","timestamp":"2020-06-18 19:55:42"},{"nodeID":"552638","text":"Anon: Rocco Forte :  if they catch the disease","type":"L","timestamp":"2020-06-18 19:55:43"},{"nodeID":"552639","text":"Default Transition","type":"TA","timestamp":"2020-06-18 19:55:43","scheme":"Default Transition","schemeID":"82"},{"nodeID":"552640","text":"Default Rephrase","type":"MA","timestamp":"2020-06-18 19:55:43","scheme":"Default Rephrase","schemeID":"144"},{"nodeID":"552641","text":"Restating","type":"YA","timestamp":"2020-06-18 19:55:43","scheme":"Restating","schemeID":"101"},{"nodeID":"552642","text":"Default Conflict","type":"CA","timestamp":"2020-06-18 19:55:43","scheme":"Default Conflict","schemeID":"71"},{"nodeID":"552643","text":"Challenging","type":"YA","timestamp":"2020-06-18 19:55:43","scheme":"Challenging","schemeID":"79"},{"nodeID":"552644","text":"Default Conflict","type":"CA","timestamp":"2020-06-18 19:55:43","scheme":"Default Conflict","schemeID":"71"},{"nodeID":"552645","text":"Challenging","type":"YA","timestamp":"2020-06-18 19:55:44","scheme":"Challenging","schemeID":"79"}],"edges":[{"edgeID":"724203","fromID":"552499","toID":"552501","formEdgeID":null},{"edgeID":"724204","fromID":"552497","toID":"552499","formEdgeID":null},{"edgeID":"724205","fromID":"552505","toID":"552509","formEdgeID":null},{"edgeID":"724206","fromID":"552509","toID":"552501","formEdgeID":null},{"edgeID":"724207","fromID":"552497","toID":"552511","formEdgeID":null},{"edgeID":"724208","fromID":"552511","toID":"552505","formEdgeID":null},{"edgeID":"724209","fromID":"552514","toID":"552516","formEdgeID":null},{"edgeID":"724210","fromID":"552512","toID":"552514","formEdgeID":null},{"edgeID":"724211","fromID":"552505","toID":"552520","formEdgeID":null},{"edgeID":"724212","fromID":"552520","toID":"552512","formEdgeID":null},{"edgeID":"724213","fromID":"552524","toID":"552526","formEdgeID":null},{"edgeID":"724214","fromID":"552522","toID":"552524","formEdgeID":null},{"edgeID":"724215","fromID":"552512","toID":"552530","formEdgeID":null},{"edgeID":"724216","fromID":"552530","toID":"552522","formEdgeID":null},{"edgeID":"724217","fromID":"552536","toID":"552538","formEdgeID":null},{"edgeID":"724218","fromID":"552534","toID":"552536","formEdgeID":null},{"edgeID":"724219","fromID":"552522","toID":"552541","formEdgeID":null},{"edgeID":"724220","fromID":"552541","toID":"552534","formEdgeID":null},{"edgeID":"724221","fromID":"552545","toID":"552546","formEdgeID":null},{"edgeID":"724222","fromID":"552543","toID":"552545","formEdgeID":null},{"edgeID":"724223","fromID":"552534","toID":"552548","formEdgeID":null},{"edgeID":"724224","fromID":"552548","toID":"552543","formEdgeID":null},{"edgeID":"724225","fromID":"552546","toID":"552549","formEdgeID":null},{"edgeID":"724226","fromID":"552549","toID":"552538","formEdgeID":null},{"edgeID":"724227","fromID":"552548","toID":"552550","formEdgeID":null},{"edgeID":"724228","fromID":"552550","toID":"552549","formEdgeID":null},{"edgeID":"724229","fromID":"552516","toID":"552551","formEdgeID":null},{"edgeID":"724230","fromID":"552551","toID":"552526","formEdgeID":null},{"edgeID":"724231","fromID":"552530","toID":"552552","formEdgeID":null},{"edgeID":"724232","fromID":"552552","toID":"552551","formEdgeID":null},{"edgeID":"724233","fromID":"552538","toID":"552553","formEdgeID":null},{"edgeID":"724234","fromID":"552553","toID":"552526","formEdgeID":null},{"edgeID":"724235","fromID":"552541","toID":"552554","formEdgeID":null},{"edgeID":"724236","fromID":"552554","toID":"552553","formEdgeID":null},{"edgeID":"724237","fromID":"552557","toID":"552558","formEdgeID":null},{"edgeID":"724238","fromID":"552556","toID":"552557","formEdgeID":null},{"edgeID":"724239","fromID":"552543","toID":"552560","formEdgeID":null},{"edgeID":"724240","fromID":"552560","toID":"552556","formEdgeID":null},{"edgeID":"724241","fromID":"552558","toID":"552561","formEdgeID":null},{"edgeID":"724242","fromID":"552561","toID":"552546","formEdgeID":null},{"edgeID":"724243","fromID":"552560","toID":"552562","formEdgeID":null},{"edgeID":"724244","fromID":"552562","toID":"552561","formEdgeID":null},{"edgeID":"724245","fromID":"552564","toID":"552565","formEdgeID":null},{"edgeID":"724246","fromID":"552563","toID":"552564","formEdgeID":null},{"edgeID":"724247","fromID":"552556","toID":"552567","formEdgeID":null},{"edgeID":"724248","fromID":"552567","toID":"552563","formEdgeID":null},{"edgeID":"724249","fromID":"552569","toID":"552570","formEdgeID":null},{"edgeID":"724250","fromID":"552568","toID":"552569","formEdgeID":null},{"edgeID":"724251","fromID":"552563","toID":"552572","formEdgeID":null},{"edgeID":"724252","fromID":"552572","toID":"552568","formEdgeID":null},{"edgeID":"724253","fromID":"552574","toID":"552575","formEdgeID":null},{"edgeID":"724254","fromID":"552573","toID":"552574","formEdgeID":null},{"edgeID":"724255","fromID":"552570","toID":"552577","formEdgeID":null},{"edgeID":"724256","fromID":"552577","toID":"552565","formEdgeID":null},{"edgeID":"724257","fromID":"552572","toID":"552578","formEdgeID":null},{"edgeID":"724258","fromID":"552578","toID":"552577","formEdgeID":null},{"edgeID":"724259","fromID":"552575","toID":"552579","formEdgeID":null},{"edgeID":"724260","fromID":"552579","toID":"552558","formEdgeID":null},{"edgeID":"724261","fromID":"552556","toID":"552580","formEdgeID":null},{"edgeID":"724262","fromID":"552580","toID":"552573","formEdgeID":null},{"edgeID":"724263","fromID":"552580","toID":"552581","formEdgeID":null},{"edgeID":"724264","fromID":"552581","toID":"552579","formEdgeID":null},{"edgeID":"724265","fromID":"552583","toID":"552584","formEdgeID":null},{"edgeID":"724266","fromID":"552582","toID":"552583","formEdgeID":null},{"edgeID":"724267","fromID":"552573","toID":"552586","formEdgeID":null},{"edgeID":"724268","fromID":"552586","toID":"552582","formEdgeID":null},{"edgeID":"724269","fromID":"552584","toID":"552587","formEdgeID":null},{"edgeID":"724270","fromID":"552587","toID":"552575","formEdgeID":null},{"edgeID":"724271","fromID":"552586","toID":"552588","formEdgeID":null},{"edgeID":"724272","fromID":"552588","toID":"552587","formEdgeID":null},{"edgeID":"724273","fromID":"552590","toID":"552591","formEdgeID":null},{"edgeID":"724274","fromID":"552589","toID":"552590","formEdgeID":null},{"edgeID":"724275","fromID":"552582","toID":"552593","formEdgeID":null},{"edgeID":"724276","fromID":"552593","toID":"552589","formEdgeID":null},{"edgeID":"724277","fromID":"552591","toID":"552594","formEdgeID":null},{"edgeID":"724278","fromID":"552594","toID":"552584","formEdgeID":null},{"edgeID":"724279","fromID":"552593","toID":"552595","formEdgeID":null},{"edgeID":"724280","fromID":"552595","toID":"552594","formEdgeID":null},{"edgeID":"724281","fromID":"552597","toID":"552598","formEdgeID":null},{"edgeID":"724282","fromID":"552596","toID":"552597","formEdgeID":null},{"edgeID":"724283","fromID":"552589","toID":"552600","formEdgeID":null},{"edgeID":"724284","fromID":"552600","toID":"552596","formEdgeID":null},{"edgeID":"724285","fromID":"552602","toID":"552603","formEdgeID":null},{"edgeID":"724286","fromID":"552601","toID":"552602","formEdgeID":null},{"edgeID":"724287","fromID":"552596","toID":"552605","formEdgeID":null},{"edgeID":"724288","fromID":"552605","toID":"552601","formEdgeID":null},{"edgeID":"724289","fromID":"552607","toID":"552608","formEdgeID":null},{"edgeID":"724290","fromID":"552606","toID":"552607","formEdgeID":null},{"edgeID":"724291","fromID":"552601","toID":"552610","formEdgeID":null},{"edgeID":"724292","fromID":"552610","toID":"552606","formEdgeID":null},{"edgeID":"724293","fromID":"552612","toID":"552613","formEdgeID":null},{"edgeID":"724294","fromID":"552611","toID":"552612","formEdgeID":null},{"edgeID":"724295","fromID":"552606","toID":"552615","formEdgeID":null},{"edgeID":"724296","fromID":"552615","toID":"552611","formEdgeID":null},{"edgeID":"724297","fromID":"552617","toID":"552618","formEdgeID":null},{"edgeID":"724298","fromID":"552616","toID":"552617","formEdgeID":null},{"edgeID":"724299","fromID":"552611","toID":"552620","formEdgeID":null},{"edgeID":"724300","fromID":"552620","toID":"552616","formEdgeID":null},{"edgeID":"724301","fromID":"552622","toID":"552623","formEdgeID":null},{"edgeID":"724302","fromID":"552621","toID":"552622","formEdgeID":null},{"edgeID":"724303","fromID":"552623","toID":"552625","formEdgeID":null},{"edgeID":"724304","fromID":"552625","toID":"552618","formEdgeID":null},{"edgeID":"724305","fromID":"552616","toID":"552626","formEdgeID":null},{"edgeID":"724306","fromID":"552626","toID":"552621","formEdgeID":null},{"edgeID":"724307","fromID":"552626","toID":"552627","formEdgeID":null},{"edgeID":"724308","fromID":"552627","toID":"552625","formEdgeID":null},{"edgeID":"724309","fromID":"552629","toID":"552630","formEdgeID":null},{"edgeID":"724310","fromID":"552628","toID":"552629","formEdgeID":null},{"edgeID":"724311","fromID":"552630","toID":"552632","formEdgeID":null},{"edgeID":"724312","fromID":"552632","toID":"552613","formEdgeID":null},{"edgeID":"724313","fromID":"552611","toID":"552633","formEdgeID":null},{"edgeID":"724314","fromID":"552633","toID":"552628","formEdgeID":null},{"edgeID":"724315","fromID":"552633","toID":"552634","formEdgeID":null},{"edgeID":"724316","fromID":"552634","toID":"552632","formEdgeID":null},{"edgeID":"724317","fromID":"552636","toID":"552637","formEdgeID":null},{"edgeID":"724318","fromID":"552635","toID":"552636","formEdgeID":null},{"edgeID":"724319","fromID":"552628","toID":"552639","formEdgeID":null},{"edgeID":"724320","fromID":"552639","toID":"552635","formEdgeID":null},{"edgeID":"724321","fromID":"552637","toID":"552640","formEdgeID":null},{"edgeID":"724322","fromID":"552640","toID":"552630","formEdgeID":null},{"edgeID":"724323","fromID":"552639","toID":"552641","formEdgeID":null},{"edgeID":"724324","fromID":"552641","toID":"552640","formEdgeID":null},{"edgeID":"724325","fromID":"552598","toID":"552642","formEdgeID":null},{"edgeID":"724326","fromID":"552642","toID":"552584","formEdgeID":null},{"edgeID":"724327","fromID":"552600","toID":"552643","formEdgeID":null},{"edgeID":"724328","fromID":"552643","toID":"552642","formEdgeID":null},{"edgeID":"724329","fromID":"552603","toID":"552602","formEdgeID":null},{"edgeID":"724330","fromID":"552603","toID":"552644","formEdgeID":null},{"edgeID":"724331","fromID":"552644","toID":"552584","formEdgeID":null},{"edgeID":"724332","fromID":"552605","toID":"552645","formEdgeID":null},{"edgeID":"724333","fromID":"552645","toID":"552644","formEdgeID":null}],"locutions":[{"nodeID":"552497","personID":"3812","timestamp":"2020-06-18 19:55:44","start":"2020-05-28 23:17:33","end":null,"source":null},{"nodeID":"552505","personID":"3914","timestamp":"2020-06-18 19:55:44","start":"2020-05-28 23:17:36","end":null,"source":null},{"nodeID":"552512","personID":"3914","timestamp":"2020-06-18 19:55:44","start":"2020-05-28 23:17:39","end":null,"source":null},{"nodeID":"552522","personID":"3914","timestamp":"2020-06-18 19:55:44","start":"2020-05-28 23:17:40","end":null,"source":null},{"nodeID":"552534","personID":"3812","timestamp":"2020-06-18 19:55:44","start":"2020-05-28 23:17:47","end":null,"source":null},{"nodeID":"552543","personID":"3812","timestamp":"2020-06-18 19:55:44","start":"2020-05-28 23:17:47","end":null,"source":null},{"nodeID":"552556","personID":"3812","timestamp":"2020-06-18 19:55:44","start":"2020-05-28 23:17:48","end":null,"source":null},{"nodeID":"552563","personID":"3812","timestamp":"2020-06-18 19:55:44","start":"2020-05-28 23:17:49","end":null,"source":null},{"nodeID":"552568","personID":"3812","timestamp":"2020-06-18 19:55:44","start":"2020-05-28 23:17:49","end":null,"source":null},{"nodeID":"552573","personID":"3914","timestamp":"2020-06-18 19:55:44","start":"2020-05-28 23:17:50","end":null,"source":null},{"nodeID":"552582","personID":"3914","timestamp":"2020-06-18 19:55:44","start":"2020-05-28 23:17:52","end":null,"source":null},{"nodeID":"552589","personID":"3812","timestamp":"2020-06-18 19:55:44","start":"2020-05-28 23:17:54","end":null,"source":null},{"nodeID":"552596","personID":"3812","timestamp":"2020-06-18 19:55:44","start":"2020-05-28 23:17:58","end":null,"source":null},{"nodeID":"552601","personID":"3913","timestamp":"2020-06-18 19:55:44","start":"2020-05-28 23:18:01","end":null,"source":null},{"nodeID":"552606","personID":"3914","timestamp":"2020-06-18 19:55:44","start":"2020-05-28 23:18:02","end":null,"source":null},{"nodeID":"552611","personID":"3914","timestamp":"2020-06-18 19:55:44","start":"2020-05-28 23:18:12","end":null,"source":null},{"nodeID":"552616","personID":"3914","timestamp":"2020-06-18 19:55:44","start":"2020-05-28 23:18:15","end":null,"source":null},{"nodeID":"552621","personID":"3914","timestamp":"2020-06-18 19:55:44","start":"2020-05-28 23:18:20","end":null,"source":null},{"nodeID":"552628","personID":"3914","timestamp":"2020-06-18 19:55:44","start":"2020-05-28 23:18:28","end":null,"source":null},{"nodeID":"552635","personID":"3914","timestamp":"2020-06-18 19:55:44","start":"2020-05-28 23:18:37","end":null,"source":null},{"nodeID":"552497","personID":"3812","timestamp":"2020-07-22 14:27:45","start":"2020-05-28 23:17:33","end":null,"source":null},{"nodeID":"552522","personID":"3914","timestamp":"2020-07-22 14:27:45","start":"2020-05-28 23:17:40","end":null,"source":null},{"nodeID":"552582","personID":"3914","timestamp":"2020-07-22 14:27:45","start":"2020-05-28 23:17:52","end":null,"source":null},{"nodeID":"552589","personID":"3812","timestamp":"2020-07-22 14:27:45","start":"2020-05-28 23:17:54","end":null,"source":null},{"nodeID":"552596","personID":"3812","timestamp":"2020-07-22 14:27:45","start":"2020-05-28 23:17:58","end":null,"source":null},{"nodeID":"552601","personID":"3762","timestamp":"2020-07-22 14:27:45","start":"2020-05-28 23:18:01","end":null,"source":null},{"nodeID":"552621","personID":"3914","timestamp":"2020-07-22 14:27:45","start":"2020-05-28 23:18:20","end":null,"source":null}]}