{"nodes":[{"nodeID":"656777","text":"Michael Forsyth : How are you going to enforce that?","type":"L","timestamp":"2021-02-18 19:33:51"},{"nodeID":"656779","text":"Jeane Freeman can not enforce that","type":"I","timestamp":"2021-02-18 19:33:51"},{"nodeID":"656780","text":"xiyuan: Michael Forsyth : How are you going to enforce that?","type":"L","timestamp":"2021-02-18 19:33:52"},{"nodeID":"656781","text":"Michael Forsyth : How are you going to enforce it when people can fly into England and go to Scotland.","type":"L","timestamp":"2021-02-18 19:33:52"},{"nodeID":"656783","text":"Jeane Freeman can  enforce it when people can fly into England and go to Scotland by xxx","type":"I","timestamp":"2021-02-18 19:33:53"},{"nodeID":"656784","text":"xiyuan: Michael Forsyth : How are you going to enforce it when people can fly into England and go to Scotland.","type":"L","timestamp":"2021-02-18 19:33:53"},{"nodeID":"656788","text":"xiyuan: Jeane Freeman : Exactly.","type":"L","timestamp":"2021-02-18 19:33:54"},{"nodeID":"656789","text":"Jeane Freeman : And the point goes back to you and your party","type":"L","timestamp":"2021-02-18 19:33:54"},{"nodeID":"656791","text":"the point goes back to Michael Forsyth and Michael Forsyth's party","type":"I","timestamp":"2021-02-18 19:33:55"},{"nodeID":"656792","text":"xiyuan: Jeane Freeman : And the point goes back to you and your party","type":"L","timestamp":"2021-02-18 19:33:55"},{"nodeID":"656793","text":"Jeane Freeman : Exactly.","type":"L","timestamp":"2021-02-18 19:33:56"},{"nodeID":"656797","text":"Fiona Bruce : No, it could come back to you, Jeane.","type":"L","timestamp":"2021-02-18 19:33:57"},{"nodeID":"656799","text":"the point could come back to Jeane Freeman","type":"I","timestamp":"2021-02-18 19:33:57"},{"nodeID":"656800","text":"xiyuan: Fiona Bruce : No, it could come back to you, Jeane.","type":"L","timestamp":"2021-02-18 19:33:58"},{"nodeID":"656804","text":"Fiona Bruce : what about people who arrive in England, drive up and want to go to Scotland?","type":"L","timestamp":"2021-02-18 19:33:58"},{"nodeID":"656806","text":"for people who arrive in England, drive up and want to go to Scotland, we should xxx","type":"I","timestamp":"2021-02-18 19:33:59"},{"nodeID":"656807","text":"xiyuan: Fiona Bruce : what about people who arrive in England, drive up and want to go to Scotland?","type":"L","timestamp":"2021-02-18 19:33:59"},{"nodeID":"656809","text":"Jeane Freeman : There's two things we will do.","type":"L","timestamp":"2021-02-18 19:33:59"},{"nodeID":"656811","text":"there are two things we will do for people who arrive in England, drive up and want to go to Scotland","type":"I","timestamp":"2021-02-18 19:34:00"},{"nodeID":"656812","text":"xiyuan: Jeane Freeman : There's two things we will do.","type":"L","timestamp":"2021-02-18 19:34:00"},{"nodeID":"656814","text":"Jeane Freeman : We'll keep on the discussions across the four nations with the UK government.","type":"L","timestamp":"2021-02-18 19:34:01"},{"nodeID":"656816","text":"we will keep on the discussions across the four nations with the UK government","type":"I","timestamp":"2021-02-18 19:34:01"},{"nodeID":"656817","text":"xiyuan: Jeane Freeman : We'll keep on the discussions across the four nations with the UK government.","type":"L","timestamp":"2021-02-18 19:34:02"},{"nodeID":"656818","text":"Jeane Freeman : I had one tonight just before I came here, to try and persuade them to not stick to just the red zones","type":"L","timestamp":"2021-02-18 19:34:02"},{"nodeID":"656820","text":"Jeane Freeman had one tonight just before she came here, to try and persuade them to not stick to just the red zones","type":"I","timestamp":"2021-02-18 19:34:03"},{"nodeID":"656821","text":"xiyuan: Jeane Freeman : I had one tonight just before I came here, to try and persuade them to not stick to just the red zones","type":"L","timestamp":"2021-02-18 19:34:03"},{"nodeID":"656822","text":"xiyuan: Jeane Freeman : in the meantime, we also have to look at what we do about the land border precisely","type":"L","timestamp":"2021-02-18 19:34:04"},{"nodeID":"656823","text":"xiyuan: Jeane Freeman : because of what the lady in the audience said.","type":"L","timestamp":"2021-02-18 19:34:04"},{"nodeID":"656824","text":"Jeane Freeman : in the meantime, we also have to look at what we do about the land border precisely because of what the lady in the audience said.","type":"L","timestamp":"2021-02-18 19:34:05"},{"nodeID":"656826","text":"in the meantime, we also have to look at what we do about the land border precisely because of what the lady in the audience said","type":"I","timestamp":"2021-02-18 19:34:05"},{"nodeID":"656827","text":"xiyuan: Jeane Freeman : in the meantime, we also have to look at what we do about the land border precisely because of what the lady in the audience said.","type":"L","timestamp":"2021-02-18 19:34:06"},{"nodeID":"656830","text":"Jeane Freeman : Most international travel into Scotland is routed through the big hubs around London, Manchester and elsewhere.","type":"L","timestamp":"2021-02-18 19:34:06"},{"nodeID":"656832","text":"most international travel into Scotland is routed through the big hubs around London, Manchester and elsewhere","type":"I","timestamp":"2021-02-18 19:34:07"},{"nodeID":"656833","text":"xiyuan: Jeane Freeman : Most international travel into Scotland is routed through the big hubs around London, Manchester and elsewhere.","type":"L","timestamp":"2021-02-18 19:34:07"},{"nodeID":"656835","text":"Fiona Bruce : Have you got a plan?","type":"L","timestamp":"2021-02-18 19:34:08"},{"nodeID":"656837","text":"Jeane Freeman got a plan or not","type":"I","timestamp":"2021-02-18 19:34:08"},{"nodeID":"656838","text":"xiyuan: Fiona Bruce : Have you got a plan?","type":"L","timestamp":"2021-02-18 19:34:08"},{"nodeID":"656840","text":"Jeane Freeman : What you can't have is people coming in, getting on public transport, coming up to Scotland","type":"L","timestamp":"2021-02-18 19:34:09"},{"nodeID":"656842","text":"what you can't have is people coming in, getting on public transport, coming up to Scotland","type":"I","timestamp":"2021-02-18 19:34:09"},{"nodeID":"656843","text":"xiyuan: Jeane Freeman : What you can't have is people coming in, getting on public transport, coming up to Scotland","type":"L","timestamp":"2021-02-18 19:34:10"},{"nodeID":"656845","text":"Jeane Freeman : we don't know about that","type":"L","timestamp":"2021-02-18 19:34:10"},{"nodeID":"656847","text":"we don't know about people coming in, getting on public transport, coming up to Scotland","type":"I","timestamp":"2021-02-18 19:34:11"},{"nodeID":"656848","text":"xiyuan: Jeane Freeman : we don't know about that","type":"L","timestamp":"2021-02-18 19:34:11"},{"nodeID":"656850","text":"Jeane Freeman : they're not required to quarantine in a way that we can manage.","type":"L","timestamp":"2021-02-18 19:34:12"},{"nodeID":"656852","text":"people are not required to quarantine in a way that we can manage","type":"I","timestamp":"2021-02-18 19:34:12"},{"nodeID":"656853","text":"xiyuan: Jeane Freeman : they're not required to quarantine in a way that we can manage.","type":"L","timestamp":"2021-02-18 19:34:13"},{"nodeID":"656855","text":"Jeane Freeman : So we have to consider what our options are about that land border.","type":"L","timestamp":"2021-02-18 19:34:13"},{"nodeID":"656857","text":"we have to consider what our options are about that land border","type":"I","timestamp":"2021-02-18 19:34:14"},{"nodeID":"656858","text":"xiyuan: Jeane Freeman : So we have to consider what our options are about that land border.","type":"L","timestamp":"2021-02-18 19:34:14"},{"nodeID":"656863","text":"Jeane Freeman : Now, I would rather that wasn't the case, to be honest.","type":"L","timestamp":"2021-02-18 19:34:15"},{"nodeID":"656865","text":"Jeane Freeman would rather that wasn't the case","type":"I","timestamp":"2021-02-18 19:34:15"},{"nodeID":"656866","text":"xiyuan: Jeane Freeman : Now, I would rather that wasn't the case, to be honest.","type":"L","timestamp":"2021-02-18 19:34:16"},{"nodeID":"656868","text":"Jeane Freeman : I would rather across the four nations we were take","type":"L","timestamp":"2021-02-18 19:34:16"},{"nodeID":"656870","text":"Jeane Freeman would rather across the four nations we were take","type":"I","timestamp":"2021-02-18 19:34:17"},{"nodeID":"656871","text":"xiyuan: Jeane Freeman : I would rather across the four nations we were take","type":"L","timestamp":"2021-02-18 19:34:17"},{"nodeID":"1017984","text":"Assertive Questioning","type":"YA","timestamp":"2022-06-20 22:26:18","scheme":"AssertiveQuestioning","schemeID":"73"},{"nodeID":"1017985","text":"Assertive Questioning","type":"YA","timestamp":"2022-06-20 22:26:21","scheme":"AssertiveQuestioning","schemeID":"73"},{"nodeID":"1017986","text":"Default Transition","type":"TA","timestamp":"2022-06-20 22:26:23","scheme":"Default Transition","schemeID":"82"},{"nodeID":"1017987","text":"Default Rephrase","type":"MA","timestamp":"2022-06-20 22:26:23","scheme":"Default Rephrase","schemeID":"144"},{"nodeID":"1017988","text":"Restating","type":"YA","timestamp":"2022-06-20 22:26:23","scheme":"Restating","schemeID":"101"},{"nodeID":"1017989","text":"Asserting","type":"YA","timestamp":"2022-06-20 22:26:24","scheme":"Asserting","schemeID":"74"},{"nodeID":"1017990","text":"Default Transition","type":"TA","timestamp":"2022-06-20 22:26:27","scheme":"Default Transition","schemeID":"82"},{"nodeID":"1017991","text":"Agreeing","type":"YA","timestamp":"2022-06-20 22:26:27","scheme":"Agreeing","schemeID":"77"},{"nodeID":"1017992","text":"Default Transition","type":"TA","timestamp":"2022-06-20 22:26:27","scheme":"Default Transition","schemeID":"82"},{"nodeID":"1017993","text":"Asserting","type":"YA","timestamp":"2022-06-20 22:26:28","scheme":"Asserting","schemeID":"74"},{"nodeID":"1017994","text":"Default Transition","type":"TA","timestamp":"2022-06-20 22:26:29","scheme":"Default Transition","schemeID":"82"},{"nodeID":"1017995","text":"Default Conflict","type":"CA","timestamp":"2022-06-20 22:26:29","scheme":"Default Conflict","schemeID":"71"},{"nodeID":"1017996","text":"Disagreeing","type":"YA","timestamp":"2022-06-20 22:26:29","scheme":"Disagreeing","schemeID":"78"},{"nodeID":"1017997","text":"Pure Questioning","type":"YA","timestamp":"2022-06-20 22:26:30","scheme":"PureQuestioning","schemeID":"91"},{"nodeID":"1017998","text":"Default Transition","type":"TA","timestamp":"2022-06-20 22:26:31","scheme":"Default Transition","schemeID":"82"},{"nodeID":"1017999","text":"Default Illocuting","type":"YA","timestamp":"2022-06-20 22:26:32","scheme":"Default Illocuting","schemeID":"168"},{"nodeID":"1018000","text":"Default Transition","type":"TA","timestamp":"2022-06-20 22:26:33","scheme":"Default Transition","schemeID":"82"},{"nodeID":"1018001","text":"Asserting","type":"YA","timestamp":"2022-06-20 22:26:34","scheme":"Asserting","schemeID":"74"},{"nodeID":"1018002","text":"Asserting","type":"YA","timestamp":"2022-06-20 22:26:36","scheme":"Asserting","schemeID":"74"},{"nodeID":"1018003","text":"Asserting","type":"YA","timestamp":"2022-06-20 22:26:40","scheme":"Asserting","schemeID":"74"},{"nodeID":"1018004","text":"Default Transition","type":"TA","timestamp":"2022-06-20 22:26:41","scheme":"Default Transition","schemeID":"82"},{"nodeID":"1018005","text":"Default Transition","type":"TA","timestamp":"2022-06-20 22:26:41","scheme":"Default Transition","schemeID":"82"},{"nodeID":"1018006","text":"Asserting","type":"YA","timestamp":"2022-06-20 22:26:42","scheme":"Asserting","schemeID":"74"},{"nodeID":"1018007","text":"Default Transition","type":"TA","timestamp":"2022-06-20 22:26:44","scheme":"Default Transition","schemeID":"82"},{"nodeID":"1018008","text":"Pure Questioning","type":"YA","timestamp":"2022-06-20 22:26:44","scheme":"PureQuestioning","schemeID":"91"},{"nodeID":"1018009","text":"Default Transition","type":"TA","timestamp":"2022-06-20 22:26:46","scheme":"Default Transition","schemeID":"82"},{"nodeID":"1018010","text":"Asserting","type":"YA","timestamp":"2022-06-20 22:26:46","scheme":"Asserting","schemeID":"74"},{"nodeID":"1018011","text":"Default Transition","type":"TA","timestamp":"2022-06-20 22:26:48","scheme":"Default Transition","schemeID":"82"},{"nodeID":"1018012","text":"Asserting","type":"YA","timestamp":"2022-06-20 22:26:49","scheme":"Asserting","schemeID":"74"},{"nodeID":"1018013","text":"Default Transition","type":"TA","timestamp":"2022-06-20 22:26:50","scheme":"Default Transition","schemeID":"82"},{"nodeID":"1018014","text":"Asserting","type":"YA","timestamp":"2022-06-20 22:26:51","scheme":"Asserting","schemeID":"74"},{"nodeID":"1018015","text":"Default Transition","type":"TA","timestamp":"2022-06-20 22:26:52","scheme":"Default Transition","schemeID":"82"},{"nodeID":"1018016","text":"Asserting","type":"YA","timestamp":"2022-06-20 22:26:53","scheme":"Asserting","schemeID":"74"},{"nodeID":"1018017","text":"Default Transition","type":"TA","timestamp":"2022-06-20 22:26:54","scheme":"Default Transition","schemeID":"82"},{"nodeID":"1018018","text":"Default Inference","type":"RA","timestamp":"2022-06-20 22:26:54","scheme":"Default Inference","schemeID":"72"},{"nodeID":"1018019","text":"Default Transition","type":"TA","timestamp":"2022-06-20 22:26:54","scheme":"Default Transition","schemeID":"82"},{"nodeID":"1018020","text":"Arguing","type":"YA","timestamp":"2022-06-20 22:26:54","scheme":"Arguing","schemeID":"80"},{"nodeID":"1018021","text":"Asserting","type":"YA","timestamp":"2022-06-20 22:26:55","scheme":"Asserting","schemeID":"74"},{"nodeID":"1018022","text":"Default Transition","type":"TA","timestamp":"2022-06-20 22:26:56","scheme":"Default Transition","schemeID":"82"},{"nodeID":"1018023","text":"Asserting","type":"YA","timestamp":"2022-06-20 22:26:57","scheme":"Asserting","schemeID":"74"},{"nodeID":"1018024","text":"Default Transition","type":"TA","timestamp":"2022-06-20 22:26:59","scheme":"Default Transition","schemeID":"82"},{"nodeID":"1018025","text":"Default Inference","type":"RA","timestamp":"2022-06-20 22:26:59","scheme":"Default Inference","schemeID":"72"},{"nodeID":"1018026","text":"Default Transition","type":"TA","timestamp":"2022-06-20 22:26:59","scheme":"Default Transition","schemeID":"82"},{"nodeID":"1018027","text":"Default Rephrase","type":"MA","timestamp":"2022-06-20 22:26:59","scheme":"Default Rephrase","schemeID":"144"},{"nodeID":"1018028","text":"Default Rephrase","type":"MA","timestamp":"2022-06-20 22:26:59","scheme":"Default Rephrase","schemeID":"144"},{"nodeID":"1018029","text":"Restating","type":"YA","timestamp":"2022-06-20 22:26:59","scheme":"Restating","schemeID":"101"},{"nodeID":"1018030","text":"Restating","type":"YA","timestamp":"2022-06-20 22:26:59","scheme":"Restating","schemeID":"101"}],"edges":[{"edgeID":"1344515","fromID":"1017984","toID":"656779","formEdgeID":null},{"edgeID":"1344516","fromID":"656777","toID":"1017984","formEdgeID":null},{"edgeID":"1344517","fromID":"1017985","toID":"656783","formEdgeID":null},{"edgeID":"1344518","fromID":"656781","toID":"1017985","formEdgeID":null},{"edgeID":"1344519","fromID":"656777","toID":"1017986","formEdgeID":null},{"edgeID":"1344520","fromID":"1017986","toID":"656781","formEdgeID":null},{"edgeID":"1344521","fromID":"656783","toID":"1017987","formEdgeID":null},{"edgeID":"1344522","fromID":"1017987","toID":"656779","formEdgeID":null},{"edgeID":"1344523","fromID":"1017986","toID":"1017988","formEdgeID":null},{"edgeID":"1344524","fromID":"1017988","toID":"1017987","formEdgeID":null},{"edgeID":"1344525","fromID":"1017989","toID":"656791","formEdgeID":null},{"edgeID":"1344526","fromID":"656789","toID":"1017989","formEdgeID":null},{"edgeID":"1344527","fromID":"656781","toID":"1017990","formEdgeID":null},{"edgeID":"1344528","fromID":"1017990","toID":"656793","formEdgeID":null},{"edgeID":"1344529","fromID":"656793","toID":"1017991","formEdgeID":null},{"edgeID":"1344530","fromID":"1017991","toID":"656783","formEdgeID":null},{"edgeID":"1344531","fromID":"656793","toID":"1017992","formEdgeID":null},{"edgeID":"1344532","fromID":"1017992","toID":"656789","formEdgeID":null},{"edgeID":"1344533","fromID":"1017993","toID":"656799","formEdgeID":null},{"edgeID":"1344534","fromID":"656797","toID":"1017993","formEdgeID":null},{"edgeID":"1344535","fromID":"656789","toID":"1017994","formEdgeID":null},{"edgeID":"1344536","fromID":"1017994","toID":"656797","formEdgeID":null},{"edgeID":"1344537","fromID":"656799","toID":"1017995","formEdgeID":null},{"edgeID":"1344538","fromID":"1017995","toID":"656791","formEdgeID":null},{"edgeID":"1344539","fromID":"1017994","toID":"1017996","formEdgeID":null},{"edgeID":"1344540","fromID":"1017996","toID":"1017995","formEdgeID":null},{"edgeID":"1344541","fromID":"1017997","toID":"656806","formEdgeID":null},{"edgeID":"1344542","fromID":"656804","toID":"1017997","formEdgeID":null},{"edgeID":"1344543","fromID":"656797","toID":"1017998","formEdgeID":null},{"edgeID":"1344544","fromID":"1017998","toID":"656804","formEdgeID":null},{"edgeID":"1344545","fromID":"1017999","toID":"656811","formEdgeID":null},{"edgeID":"1344546","fromID":"656809","toID":"1017999","formEdgeID":null},{"edgeID":"1344547","fromID":"656804","toID":"1018000","formEdgeID":null},{"edgeID":"1344548","fromID":"1018000","toID":"656809","formEdgeID":null},{"edgeID":"1344549","fromID":"1018001","toID":"656816","formEdgeID":null},{"edgeID":"1344550","fromID":"656814","toID":"1018001","formEdgeID":null},{"edgeID":"1344551","fromID":"1018002","toID":"656820","formEdgeID":null},{"edgeID":"1344552","fromID":"656818","toID":"1018002","formEdgeID":null},{"edgeID":"1344553","fromID":"1018003","toID":"656826","formEdgeID":null},{"edgeID":"1344554","fromID":"656824","toID":"1018003","formEdgeID":null},{"edgeID":"1344555","fromID":"656818","toID":"1018004","formEdgeID":null},{"edgeID":"1344556","fromID":"1018004","toID":"656824","formEdgeID":null},{"edgeID":"1344557","fromID":"656814","toID":"1018005","formEdgeID":null},{"edgeID":"1344558","fromID":"1018005","toID":"656818","formEdgeID":null},{"edgeID":"1344559","fromID":"1018006","toID":"656832","formEdgeID":null},{"edgeID":"1344560","fromID":"656830","toID":"1018006","formEdgeID":null},{"edgeID":"1344561","fromID":"656824","toID":"1018007","formEdgeID":null},{"edgeID":"1344562","fromID":"1018007","toID":"656830","formEdgeID":null},{"edgeID":"1344563","fromID":"1018008","toID":"656837","formEdgeID":null},{"edgeID":"1344564","fromID":"656835","toID":"1018008","formEdgeID":null},{"edgeID":"1344565","fromID":"656830","toID":"1018009","formEdgeID":null},{"edgeID":"1344566","fromID":"1018009","toID":"656835","formEdgeID":null},{"edgeID":"1344567","fromID":"1018010","toID":"656842","formEdgeID":null},{"edgeID":"1344568","fromID":"656840","toID":"1018010","formEdgeID":null},{"edgeID":"1344569","fromID":"656835","toID":"1018011","formEdgeID":null},{"edgeID":"1344570","fromID":"1018011","toID":"656840","formEdgeID":null},{"edgeID":"1344571","fromID":"1018012","toID":"656847","formEdgeID":null},{"edgeID":"1344572","fromID":"656845","toID":"1018012","formEdgeID":null},{"edgeID":"1344573","fromID":"656840","toID":"1018013","formEdgeID":null},{"edgeID":"1344574","fromID":"1018013","toID":"656845","formEdgeID":null},{"edgeID":"1344575","fromID":"1018014","toID":"656852","formEdgeID":null},{"edgeID":"1344576","fromID":"656850","toID":"1018014","formEdgeID":null},{"edgeID":"1344577","fromID":"656845","toID":"1018015","formEdgeID":null},{"edgeID":"1344578","fromID":"1018015","toID":"656850","formEdgeID":null},{"edgeID":"1344579","fromID":"1018016","toID":"656857","formEdgeID":null},{"edgeID":"1344580","fromID":"656855","toID":"1018016","formEdgeID":null},{"edgeID":"1344581","fromID":"656850","toID":"1018017","formEdgeID":null},{"edgeID":"1344582","fromID":"1018017","toID":"656855","formEdgeID":null},{"edgeID":"1344583","fromID":"656842","toID":"1018018","formEdgeID":null},{"edgeID":"1344584","fromID":"1018018","toID":"656857","formEdgeID":null},{"edgeID":"1344585","fromID":"656840","toID":"1018019","formEdgeID":null},{"edgeID":"1344586","fromID":"1018019","toID":"656855","formEdgeID":null},{"edgeID":"1344587","fromID":"1018019","toID":"1018020","formEdgeID":null},{"edgeID":"1344588","fromID":"1018020","toID":"1018018","formEdgeID":null},{"edgeID":"1344589","fromID":"1018021","toID":"656865","formEdgeID":null},{"edgeID":"1344590","fromID":"656863","toID":"1018021","formEdgeID":null},{"edgeID":"1344591","fromID":"656855","toID":"1018022","formEdgeID":null},{"edgeID":"1344592","fromID":"1018022","toID":"656863","formEdgeID":null},{"edgeID":"1344593","fromID":"1018023","toID":"656870","formEdgeID":null},{"edgeID":"1344594","fromID":"656868","toID":"1018023","formEdgeID":null},{"edgeID":"1344595","fromID":"656863","toID":"1018024","formEdgeID":null},{"edgeID":"1344596","fromID":"1018024","toID":"656868","formEdgeID":null},{"edgeID":"1344597","fromID":"656811","toID":"1018025","formEdgeID":null},{"edgeID":"1344598","fromID":"1018025","toID":"656806","formEdgeID":null},{"edgeID":"1344599","fromID":"656809","toID":"1018026","formEdgeID":null},{"edgeID":"1344600","fromID":"1018026","toID":"656814","formEdgeID":null},{"edgeID":"1344601","fromID":"656847","toID":"1018018","formEdgeID":null},{"edgeID":"1344602","fromID":"656852","toID":"1018018","formEdgeID":null},{"edgeID":"1344603","fromID":"656850","toID":"1018019","formEdgeID":null},{"edgeID":"1344604","fromID":"656816","toID":"1018027","formEdgeID":null},{"edgeID":"1344605","fromID":"1018027","toID":"656811","formEdgeID":null},{"edgeID":"1344606","fromID":"656820","toID":"1018028","formEdgeID":null},{"edgeID":"1344607","fromID":"1018028","toID":"656811","formEdgeID":null},{"edgeID":"1344608","fromID":"1018026","toID":"1018029","formEdgeID":null},{"edgeID":"1344609","fromID":"1018029","toID":"1018027","formEdgeID":null},{"edgeID":"1344610","fromID":"1018005","toID":"1018030","formEdgeID":null},{"edgeID":"1344611","fromID":"1018030","toID":"1018028","formEdgeID":null}],"locutions":[{"nodeID":"656777","personID":"4315","timestamp":"2021-02-18 19:34:18","start":null,"end":null,"source":null},{"nodeID":"656781","personID":"4315","timestamp":"2021-02-18 19:34:18","start":null,"end":null,"source":null},{"nodeID":"656789","personID":"4316","timestamp":"2021-02-18 19:34:18","start":null,"end":null,"source":null},{"nodeID":"656793","personID":"4316","timestamp":"2021-02-18 19:34:18","start":null,"end":null,"source":null},{"nodeID":"656797","personID":"3812","timestamp":"2021-02-18 19:34:18","start":null,"end":null,"source":null},{"nodeID":"656804","personID":"3812","timestamp":"2021-02-18 19:34:18","start":null,"end":null,"source":null},{"nodeID":"656809","personID":"4316","timestamp":"2021-02-18 19:34:18","start":null,"end":null,"source":null},{"nodeID":"656814","personID":"4316","timestamp":"2021-02-18 19:34:18","start":null,"end":null,"source":null},{"nodeID":"656818","personID":"4316","timestamp":"2021-02-18 19:34:18","start":null,"end":null,"source":null},{"nodeID":"656824","personID":"4316","timestamp":"2021-02-18 19:34:18","start":null,"end":null,"source":null},{"nodeID":"656830","personID":"4316","timestamp":"2021-02-18 19:34:18","start":null,"end":null,"source":null},{"nodeID":"656835","personID":"3812","timestamp":"2021-02-18 19:34:18","start":null,"end":null,"source":null},{"nodeID":"656840","personID":"4316","timestamp":"2021-02-18 19:34:18","start":null,"end":null,"source":null},{"nodeID":"656845","personID":"4316","timestamp":"2021-02-18 19:34:18","start":null,"end":null,"source":null},{"nodeID":"656850","personID":"4316","timestamp":"2021-02-18 19:34:18","start":null,"end":null,"source":null},{"nodeID":"656855","personID":"4316","timestamp":"2021-02-18 19:34:18","start":null,"end":null,"source":null},{"nodeID":"656863","personID":"4316","timestamp":"2021-02-18 19:34:18","start":null,"end":null,"source":null},{"nodeID":"656868","personID":"4316","timestamp":"2021-02-18 19:34:18","start":null,"end":null,"source":null},{"nodeID":"656777","personID":"4315","timestamp":"2022-06-20 22:26:59","start":null,"end":null,"source":null},{"nodeID":"656781","personID":"4315","timestamp":"2022-06-20 22:26:59","start":null,"end":null,"source":null},{"nodeID":"656789","personID":"4316","timestamp":"2022-06-20 22:26:59","start":null,"end":null,"source":null},{"nodeID":"656793","personID":"4316","timestamp":"2022-06-20 22:26:59","start":null,"end":null,"source":null},{"nodeID":"656797","personID":"3812","timestamp":"2022-06-20 22:26:59","start":null,"end":null,"source":null},{"nodeID":"656804","personID":"3812","timestamp":"2022-06-20 22:26:59","start":null,"end":null,"source":null},{"nodeID":"656809","personID":"4316","timestamp":"2022-06-20 22:26:59","start":null,"end":null,"source":null},{"nodeID":"656814","personID":"4316","timestamp":"2022-06-20 22:26:59","start":null,"end":null,"source":null},{"nodeID":"656818","personID":"4316","timestamp":"2022-06-20 22:26:59","start":null,"end":null,"source":null},{"nodeID":"656824","personID":"4316","timestamp":"2022-06-20 22:26:59","start":null,"end":null,"source":null},{"nodeID":"656830","personID":"4316","timestamp":"2022-06-20 22:26:59","start":null,"end":null,"source":null},{"nodeID":"656835","personID":"3812","timestamp":"2022-06-20 22:26:59","start":null,"end":null,"source":null},{"nodeID":"656840","personID":"4316","timestamp":"2022-06-20 22:26:59","start":null,"end":null,"source":null},{"nodeID":"656845","personID":"4316","timestamp":"2022-06-20 22:26:59","start":null,"end":null,"source":null},{"nodeID":"656850","personID":"4316","timestamp":"2022-06-20 22:26:59","start":null,"end":null,"source":null},{"nodeID":"656855","personID":"4316","timestamp":"2022-06-20 22:26:59","start":null,"end":null,"source":null},{"nodeID":"656863","personID":"4316","timestamp":"2022-06-20 22:26:59","start":null,"end":null,"source":null},{"nodeID":"656868","personID":"4316","timestamp":"2022-06-20 22:26:59","start":null,"end":null,"source":null}]}